[
  {
    "id": 1,
    "ts": "2026-07-10T18:40:38",
    "fecha": "2026-07-10",
    "pick": "PHILLIES ML",
    "team": "PHILLIES",
    "market": "ML",
    "line": null,
    "cuota": 101.0,
    "cuota_decimal": 2.01,
    "resultado": "PERDIO",
    "record": "PHILLIES ML|2026-07-10T18:40:38|ARANDU",
    "ots": "proofs\\pick_1.txt.ots",
    "sellado": true,
    "libro": "DraftKings",
    "msg_id": 37,
    "msg_texto": "ARANDU RESEARCH\nPHILLIES ML\n🎯 Apuesto a que Philadelphia Phillies gana hoy\nPhiladelphia Phillies vs Detroit Tigers — 06:40 PM\nLINEA: +101 (DraftKings) · paga 2.01x\n2026-07-10T18:40:38\nEstado: ⏳ PENDIENTE\nSHA-256: 96c1856a9295c3e2…b7d0b851\n(🔒 Verificar: aranduresearch.github.io/arandu-record)"
  }
]